[
    {
        "title": "Council Resolution of 10 November 2003 on the Communication of the European Commission \"Enhancing the Implementation of the New Approach Directives\"",
        "parent_celex": "32008D0768",
        "oj_num": "OJ C 282, 25.11.2003, p. 3-4",
        "doc_type": "C",
        "celex_num": "32003G1125(02)",
        "url": "https://eur-lex.europa.eu/legal-content/EN/AUTO/?uri=uriserv:OJ.C_.2003.282.01.0003.01.ENG&toc=OJ:C:2003:282:TOC"
    },
    {
        "title": "Directive 98/34/EC of the European Parliament and of the Council of 22 June 1998 laying down a procedure for the provision of information in the field of technical standards and regulations",
        "parent_celex": "32008D0768",
        "oj_num": "OJ L 204, 21.7.1998, p. 37-48",
        "doc_type": "L",
        "celex_num": "31998L0034",
        "url": "https://eur-lex.europa.eu/legal-content/EN/AUTO/?uri=uriserv:OJ.L_.1998.204.01.0037.01.ENG&toc=OJ:L:1998:204:TOC"
    },
    {
        "title": "Council Directive 2006/96/EC of 20 November 2006 adapting certain Directives in the field of free movement of goods, by reason of the accession of Bulgaria and Romania",
        "parent_celex": "32008D0768",
        "oj_num": "OJ L 363, 20.12.2006, p. 81-106",
        "doc_type": "L",
        "celex_num": "32006L0096",
        "url": "https://eur-lex.europa.eu/legal-content/EN/AUTO/?uri=uriserv:OJ.L_.2006.363.01.0081.01.ENG&toc=OJ:L:2006:363:TOC"
    },
    {
        "title": "93/465/EEC: Council Decision of 22 July 1993 concerning the modules for the various phases of the conformity assessment procedures and the rules for the affixing and use of the CE conformity marking, which are intended to be used in the technical harmonization directives",
        "parent_celex": "32008D0768",
        "oj_num": "OJ L 220, 30.8.1993, p. 23-39",
        "doc_type": "L",
        "celex_num": "31993D0465",
        "url": "https://eur-lex.europa.eu/legal-content/EN/AUTO/?uri=uriserv:OJ.L_.1993.220.01.0023.01.ENG&toc=OJ:L:1993:220:TOC"
    },
    {
        "title": "Council Directive 85/374/EEC of 25 July 1985 on the approximation of the laws, regulations and administrative provisions of the Member States concerning liability for defective products",
        "parent_celex": "32008D0768",
        "oj_num": "OJ L 210, 7.8.1985, p. 29-33",
        "doc_type": "L",
        "celex_num": "31985L0374",
        "url": "https://eur-lex.europa.eu/legal-content/EN/AUTO/?uri=uriserv:OJ.L_.1985.210.01.0029.01.ENG&toc=OJ:L:1985:210:TOC"
    },
    {
        "title": "Directive 1999/34/EC of the European Parliament and of the Council of 10 May 1999 amending Council Directive 85/374/EEC on the approximation of the laws, regulations and administrative provisions of the Member States concerning liability for defective products",
        "parent_celex": "32008D0768",
        "oj_num": "OJ L 141, 4.6.1999, p. 20-21",
        "doc_type": "L",
        "celex_num": "31999L0034",
        "url": "https://eur-lex.europa.eu/legal-content/EN/AUTO/?uri=uriserv:OJ.L_.1999.141.01.0020.01.ENG&toc=OJ:L:1999:141:TOC"
    }
]